getpdf/__init__.py
getpdf/get_pdf_line.py
getpdf/main.py
getpdf-0.0.6.dist-info/LICENSE
getpdf-0.0.6.dist-info/METADATA
getpdf-0.0.6.dist-info/WHEEL
getpdf-0.0.6.dist-info/entry_points.txt
getpdf-0.0.6.dist-info/top_level.txt
getpdf-0.0.6.dist-info/RECORD
