Metadata-Version: 2.1
Name: getpdf
Version: 0.0.6
Summary: Library for getting PDF  from google search
Home-page: https://github.com/perseu912/getpdf
Author: Reinan Br
Author-email: slimchatuba@gmail.com
License: MIT License
Keywords: kit tools dev works
Platform: UNKNOWN
License-File: LICENSE
Requires-Dist: requests
Requires-Dist: googlesearch-python
